netkiller/yoloutils.py
netkiller_yoloutils-0.0.2.dist-info/licenses/LICENSE
netkiller_yoloutils-0.0.2.dist-info/METADATA
netkiller_yoloutils-0.0.2.dist-info/WHEEL
netkiller_yoloutils-0.0.2.dist-info/entry_points.txt
netkiller_yoloutils-0.0.2.dist-info/top_level.txt
netkiller_yoloutils-0.0.2.dist-info/RECORD
