Metadata-Version: 2.4
Name: netkiller-yoloutils
Version: 0.0.2
Summary: YOLO label utils
Author-email: Neo <netkiller@msn.com>
License-Expression: MIT
Project-URL: Homepage, https://www.netkiller.cn
Project-URL: Issues, https://github.com/netkiller/yoloutils/issues
Classifier: Programming Language :: Python :: 3
Classifier: Operating System :: OS Independent
Requires-Python: >=3.12
License-File: LICENSE
Requires-Dist: pillow
Requires-Dist: opencv-python
Requires-Dist: pyyaml
Requires-Dist: tqdm
Requires-Dist: texttable
Requires-Dist: ultralytics
Dynamic: license-file
